email2dict/__init__.py
email2dict/py.typed
email2dict-0.1.0.post1.dist-info/LICENSE
email2dict-0.1.0.post1.dist-info/METADATA
email2dict-0.1.0.post1.dist-info/WHEEL
email2dict-0.1.0.post1.dist-info/top_level.txt
email2dict-0.1.0.post1.dist-info/RECORD
