Metadata-Version: 2.1
Name: email2dict
Version: 0.1.0.post1
Summary: Convert EmailMessage objects to dicts
Home-page: https://github.com/jwodder/email2dict
Author: John Thorvald Wodder II
Author-email: email2dict@varonathe.org
License: MIT
Project-URL: Source Code, https://github.com/jwodder/email2dict
Project-URL: Bug Tracker, https://github.com/jwodder/email2dict/issues
Keywords: comparison,e-mail,email,inspection,json
Platform: UNKNOWN
Classifier: Development Status :: 4 - Beta
Classifier: Programming Language :: Python :: 3 :: Only
Classifier: Programming Language :: Python :: 3
Classifier: Programming Language :: Python :: 3.6
Classifier: Programming Language :: Python :: 3.7
Classifier: Programming Language :: Python :: 3.8
Classifier: Programming Language :: Python :: 3.9
Classifier: Programming Language :: Python :: Implementation :: CPython
Classifier: Programming Language :: Python :: Implementation :: PyPy
Classifier: License :: OSI Approved :: MIT License
Classifier: Intended Audience :: Developers
Classifier: Topic :: Communications :: Email
Classifier: Topic :: Utilities
Classifier: Typing :: Typed
Requires-Python: ~=3.6
